KCC2020_HAR_dataset
