Metadata-Version: 2.1
Name: kcc2020-tutorial-HAR-dataset
Version: 0.1.3
Summary: UNKNOWN
Home-page: UNKNOWN
Author: Auk Kim
Author-email: kimauk@kaist.ac.kr
License: UNKNOWN
Platform: UNKNOWN
Classifier: Programming Language :: Python :: 3
Classifier: Topic :: Scientific/Engineering
Requires-Python: >=3.6
